<PAMDataset>
  <Metadata>
    <MDI key="DataType">Generic</MDI>
  </Metadata>
  <PAMRasterBand band="1">
    <Description>Band_1</Description>
    <Histograms>
      <HistItem>
        <HistMin>2.554410696029663</HistMin>
        <HistMax>6.890511035919189</HistMax>
        <BucketCount>256</BucketCount>
        <IncludeOutOfRange>1</IncludeOutOfRange>
        <Approximate>0</Approximate>
        <HistCounts>1|2|1|1|2|2|2|3|5|1|8|6|9|23|22|19|29|37|35|54|50|67|65|66|80|100|74|116|153|191|212|225|225|279|298|376|423|443|547|541|625|680|661|774|760|886|863|904|952|977|1009|967|1005|997|996|989|957|938|928|823|803|728|731|733|656|611|613|597|562|574|517|513|504|490|432|404|435|415|431|432|367|418|351|389|323|357|319|328|350|324|319|280|279|292|275|271|273|272|256|257|274|232|256|226|177|226|221|215|205|179|175|174|166|205|188|197|159|164|139|190|172|166|161|158|170|165|154|146|143|151|140|126|147|130|137|125|123|127|120|121|116|113|130|91|117|93|120|84|112|99|104|103|97|109|97|93|73|89|74|76|72|69|60|63|67|45|48|64|46|38|46|68|42|39|58|49|40|38|36|23|38|37|36|33|28|24|31|16|33|36|16|18|22|27|32|20|20|14|18|16|24|7|25|7|17|20|15|12|14|12|15|15|6|9|11|9|6|7|11|8|7|13|8|3|4|4|3|4|4|6|2|0|1|7|1|3|6|3|4|2|0|1|0|0|1|3|1|0|1|0|1|0|0|0|0|1</HistCounts>
      </HistItem>
    </Histograms>
    <Metadata>
      <MDI key="BandName">Band_1</MDI>
      <MDI key="RepresentationType">ATHEMATIC</MDI>
      <MDI key="STATISTICS_EXCLUDEDVALUES"></MDI>
      <MDI key="STATISTICS_MAXIMUM">6.8905110359192</MDI>
      <MDI key="STATISTICS_MEAN">3.8341284791695</MDI>
      <MDI key="STATISTICS_MEDIAN">nan</MDI>
      <MDI key="STATISTICS_MINIMUM">2.5544106960297</MDI>
      <MDI key="STATISTICS_SKIPFACTORX">1</MDI>
      <MDI key="STATISTICS_SKIPFACTORY">1</MDI>
      <MDI key="STATISTICS_STDDEV">0.62444024973633</MDI>
    </Metadata>
  </PAMRasterBand>
</PAMDataset>
